{
    "timestamp" : 1468501221345,
    "revision" : {
        "HEAD" : "6aa4cf1e81f61b3f595c22fe92ae54cdae5f4cc4",
        "currentBranch" : "refs/heads/master",
        "knownReferences" : [{
            "name" : "origin",
            "url" : "https://github.com/wendehals/arduino_sct_tools.git",
            "ref" : "master"
        }]
    },
    "properties" : {
        "TARGET_PLATFORM_VERSION_MAXIMUM" : "null",
        "java.version" : "1.8.0_92",
        "user.dir" : "C:\\Entwicklung\\sct-arduino-dev-ide\\git\\arduino_sct_tools\\build\\org.yakindu.sct.arduino.build",
        "os.arch" : "amd64",
        "RELEASE" : "null",
        "BUILD_ID" : "null",
        "BUILD_ALIAS" : "null",
        "JOB_NAME" : "null",
        "os.version" : "10.0",
        "BUILD_NUMBER" : "null",
        "TARGET_PLATFORM_VERSION" : "null",
        "NODE_NAME" : "null",
        "HOSTNAME" : "Asterix",
        "java.vendor" : "Oracle Corporation",
        "os.name" : "Windows 10",
        "ZIPSUFFIX" : "null",
        "WORKSPACE" : "C:\\Entwicklung\\sct-arduino-dev-ide\\git\\arduino_sct_tools\\build\\org.yakindu.sct.arduino.build"
    },
    "upstream" : null
}